README.md
setup.py
toshona/__init__.py
toshona/toshona.py
toshona.egg-info/PKG-INFO
toshona.egg-info/SOURCES.txt
toshona.egg-info/dependency_links.txt
toshona.egg-info/top_level.txt